{
  "usuarios": [
    {
      "id": 1,
      "nome": "Admin",
      "email": "admin@email.com",
      "senha": "Admin"
    }
  ],
  "categorias": [
    { "id": 1, "userId": 1, "nome": "Doce" },
    { "id": 2, "userId": 1, "nome": "Salgado" }
  ],
  "receitas": [
    {
      "id": 1,
      "userId": 1,
      "nome": "Bolo de Chocolate",
      "tempo_preparo": 45,
      "categoriaId": 1,
      "ingredientes": [1, 2],
      "modo_preparo": "Misture e asse por 40 minutos."
    }
  ],
  "estoque": [
    { 
      "id": 1,
      "userId": 1,
      "nome": "Farinha de trigo",
      "quantidade": 1,
      "unidade": "xícaras" 
    },
    { 
      "id": 2,
      "userId": 1,
      "nome": "Ovos",
      "quantidade": 2,
      "unidade": "unidades" 
    }
  ]
}